<?xml version="1.0" encoding="UTF-8" standalone="yes"?>
<Concierto>
    <fecha>22-OCT-2022</fecha>
    <hora>22:00</hora>
    <participante>
        <entrada>22:30</entrada>
        <grupo>Green Day</grupo>
    </participante>
    <participante>
        <entrada>23:15</entrada>
        <grupo>The Offspring</grupo>
    </participante>
    <participante>
        <entrada>00:00</entrada>
        <grupo>Simple Plan</grupo>
    </participante>
    <participante>
        <entrada>00:45</entrada>
        <grupo>Coldplay</grupo>
    </participante>
    <participante>
        <entrada>01:15</entrada>
        <grupo>U2</grupo>
    </participante>
</Concierto>
